MANIFEST.in
README.md
setup.py
swallow/Swallow.py
swallow/__init__.py
swallow/logger_mp.py
swallow/settings.py
swallow.egg-info/PKG-INFO
swallow.egg-info/SOURCES.txt
swallow.egg-info/dependency_links.txt
swallow.egg-info/requires.txt
swallow.egg-info/top_level.txt
swallow/inout/Algoliaio.py
swallow/inout/CSVio.py
swallow/inout/ESio.py
swallow/inout/JsonFileio.py
swallow/inout/Mongoio.py
swallow/inout/Mysqlio.py
swallow/inout/XMLio.py
swallow/inout/__init__.py
swallow/parser/__init__.py
swallow/parser/parser.py
test/__init__.py
test/test_algolia.py
test/test_csv.py
test/test_mongo.py
test/test_mysql.py