Metadata-Version: 1.0
Name: swallow
Version: 1.6.7
Summary: Swallow for data transformation
Home-page: https://github.com/pagesjaunes/swallow
Author: PagesJaunes
Author-email: fdepaulis@pagesjaunes.fr
License: UNKNOWN
Platform: UNKNOWN
